requests_seekable.py
requests_seekable-0.1.0.dist-info/licenses/LICENSE
requests_seekable-0.1.0.dist-info/METADATA
requests_seekable-0.1.0.dist-info/WHEEL
requests_seekable-0.1.0.dist-info/top_level.txt
requests_seekable-0.1.0.dist-info/RECORD
