Metadata-Version: 2.4
Name: requests-seekable
Version: 0.1.0
Summary: Seekable HTTP responses using 'Range' headers for python-requests
Author-email: Barney Gale <barney.gale@gmail.com>
License-Expression: GPL-3.0-or-later
Project-URL: Source code, https://github.com/barneygale/requests-seekable
Project-URL: Issue tracker, https://github.com/barneygale/requests-seekable/issues
Classifier: Development Status :: 4 - Beta
Classifier: Programming Language :: Python
Classifier: Programming Language :: Python :: 3
Classifier: Programming Language :: Python :: 3.9
Classifier: Programming Language :: Python :: 3.10
Classifier: Programming Language :: Python :: 3.11
Classifier: Programming Language :: Python :: 3.12
Classifier: Programming Language :: Python :: 3.13
Classifier: Programming Language :: Python :: 3.14
Requires-Python: >=3.9
License-File: LICENSE
Requires-Dist: requests
Dynamic: license-file
